{
  "// INSTRUCCIONES": "Copia este contenido a .vscode/settings.json para habilitar ESLint y Prettier automáticamente",
  "// EXTENSIONES REQUERIDAS": "ESLint (dbaeumer.vscode-eslint) y Prettier (esbenp.prettier-vscode)",
  
  "liveServer.settings.port": 5501,
  
  "editor.formatOnSave": true,
  "editor.defaultFormatter": "esbenp.prettier-vscode",
  "editor.codeActionsOnSave": {
    "source.fixAll.eslint": "explicit"
  },
  "eslint.validate": [
    "javascript"
  ],
  "files.eol": "\n",
  "editor.tabSize": 2,
  "editor.insertSpaces": true,
  "javascript.preferences.quoteStyle": "single",
  "typescript.preferences.quoteStyle": "single",
  
  "[javascript]": {
    "editor.defaultFormatter": "esbenp.prettier-vscode"
  },
  "[json]": {
    "editor.defaultFormatter": "esbenp.prettier-vscode"
  },
  "[html]": {
    "editor.defaultFormatter": "esbenp.prettier-vscode"
  },
  "[css]": {
    "editor.defaultFormatter": "esbenp.prettier-vscode"
  }
}
